MANIFEST.in
README.rst
setup.py
django_fancy_feast.egg-info/PKG-INFO
django_fancy_feast.egg-info/SOURCES.txt
django_fancy_feast.egg-info/dependency_links.txt
django_fancy_feast.egg-info/top_level.txt
fancy_feast/__init__.py
fancy_feast/forms/__init__.py
fancy_feast/forms/fields/__init__.py
fancy_feast/forms/fields/data_model_field.py
fancy_feast/forms/fields/tag_field.py
fancy_feast/forms/widgets/__init__.py
fancy_feast/forms/widgets/data_model_choice.py
fancy_feast/forms/widgets/tag_input.py
fancy_feast/static/fancy_feast/css/styles.css
fancy_feast/templates/fancy_feast/widgets/_tag_input.html